README.md
setup.py
awesome_AD/__init__.py
awesome_AD/autoDiff.py
awesome_AD/autoDiffRev.py
awesome_AD/jacobian.py
awesome_AD/jacobianRev.py
awesome_AD/root_find.py
awesome_AD.egg-info/PKG-INFO
awesome_AD.egg-info/SOURCES.txt
awesome_AD.egg-info/dependency_links.txt
awesome_AD.egg-info/requires.txt
awesome_AD.egg-info/top_level.txt