Metadata-Version: 2.1
Name: awesome-AD
Version: 0.0.3
Summary: A package of automatic differentiation with both Forward Mode and Reserve Mode
Home-page: https://github.com/berry12kiwi/cs107-FinalProject/tree/master
Author: Berry12kiwi (ac207 Group 8): Xingyu Liu, Sarah Zeng, Qinyi Chen
Author-email: charlotteliu12x@gmail.com, Sarah_zeng@college.Harvard.edu, qychen@seas.harvard.edu
License: UNKNOWN
Platform: UNKNOWN
Classifier: Programming Language :: Python :: 3
Classifier: License :: OSI Approved :: MIT License
Requires-Python: >=3.6
